tensorbay/__init__.py
tensorbay/__version__.py
tensorbay/conftest.py
tensorbay/exception.py
tensorbay/py.typed
tensorbay/apps/__init__.py
tensorbay/apps/sextant.py
tensorbay/cli/__init__.py
tensorbay/cli/auth.py
tensorbay/cli/branch.py
tensorbay/cli/cli.py
tensorbay/cli/commit.py
tensorbay/cli/config.py
tensorbay/cli/cp.py
tensorbay/cli/custom.py
tensorbay/cli/dataset.py
tensorbay/cli/draft.py
tensorbay/cli/log.py
tensorbay/cli/ls.py
tensorbay/cli/rm.py
tensorbay/cli/tag.py
tensorbay/cli/tbrn.py
tensorbay/cli/utility.py
tensorbay/client/__init__.py
tensorbay/client/cloud_storage.py
tensorbay/client/dataset.py
tensorbay/client/diff.py
tensorbay/client/gas.py
tensorbay/client/job.py
tensorbay/client/lazy.py
tensorbay/client/log.py
tensorbay/client/profile.py
tensorbay/client/requests.py
tensorbay/client/search.py
tensorbay/client/segment.py
tensorbay/client/statistics.py
tensorbay/client/status.py
tensorbay/client/struct.py
tensorbay/client/version.py
tensorbay/dataset/__init__.py
tensorbay/dataset/data.py
tensorbay/dataset/dataset.py
tensorbay/dataset/frame.py
tensorbay/dataset/segment.py
tensorbay/geometry/__init__.py
tensorbay/geometry/box.py
tensorbay/geometry/keypoint.py
tensorbay/geometry/point_list.py
tensorbay/geometry/polygon.py
tensorbay/geometry/polyline.py
tensorbay/geometry/transform.py
tensorbay/geometry/vector.py
tensorbay/healthcheck/__init__.py
tensorbay/healthcheck/basic_check.py
tensorbay/healthcheck/catalog_check.py
tensorbay/healthcheck/healthcheck.py
tensorbay/healthcheck/pipeline.py
tensorbay/healthcheck/report.py
tensorbay/label/__init__.py
tensorbay/label/attributes.py
tensorbay/label/basic.py
tensorbay/label/catalog.py
tensorbay/label/label.py
tensorbay/label/label_box.py
tensorbay/label/label_classification.py
tensorbay/label/label_keypoints.py
tensorbay/label/label_mask.py
tensorbay/label/label_polygon.py
tensorbay/label/label_polyline.py
tensorbay/label/label_sentence.py
tensorbay/label/supports.py
tensorbay/opendataset/__init__.py
tensorbay-1.24.2.dist-info/LICENSE
tensorbay-1.24.2.dist-info/METADATA
tensorbay-1.24.2.dist-info/WHEEL
tensorbay-1.24.2.dist-info/entry_points.txt
tensorbay-1.24.2.dist-info/top_level.txt
tensorbay-1.24.2.dist-info/RECORD
