Metadata-Version: 2.1
Name: tensorbay
Version: 1.24.2
Summary: Graviti TensorBay Python SDK
Home-page: https://github.com/Graviti-AI/tensorbay-python-sdk
Author: Graviti
Author-email: pypi@graviti.com
License: MIT
Keywords: graviti,tensorbay,dataset
Platform: UNKNOWN
Classifier: Development Status :: 4 - Beta
Classifier: Intended Audience :: Developers
Classifier: Intended Audience :: Science/Research
Classifier: License :: OSI Approved :: MIT License
Classifier: Operating System :: OS Independent
Classifier: Programming Language :: Python
Classifier: Programming Language :: Python :: 3
Classifier: Programming Language :: Python :: 3 :: Only
Classifier: Programming Language :: Python :: 3.6
Classifier: Programming Language :: Python :: 3.7
Classifier: Programming Language :: Python :: 3.8
Classifier: Programming Language :: Python :: 3.9
Classifier: Programming Language :: Python :: 3.10
Classifier: Topic :: Scientific/Engineering :: Artificial Intelligence
Classifier: Typing :: Typed
Requires-Python: >=3.6
Requires-Dist: click (>=7.0.0)
Requires-Dist: filetype (>=1.0.0)
Requires-Dist: numpy (>=1.16.0)
Requires-Dist: numpy-quaternion (<=2021.11.4.15.26.3,>=2021.3.17.16.51.43)
Requires-Dist: requests (>=2.4.2)
Requires-Dist: requests-toolbelt (>=0.3.0)
Requires-Dist: tqdm (>=4.14.0)
Requires-Dist: typing-extensions (>=3.7.2)
Requires-Dist: ulid-py (>=1.1.0)
Requires-Dist: urllib3 (>=1.15)
